<?xml version="1.0" encoding="UTF-8"?><record_update table="sp_row">
    <sp_row action="INSERT_OR_UPDATE">
        <class_name/>
        <order>1</order>
        <sp_column/>
        <sp_container display_value="School Office Supplies Management Homepage - Container 1">7f5d626697dc311015c7fbafe153af64</sp_container>
        <sys_class_name>sp_row</sys_class_name>
        <sys_created_by>johniel.comanda</sys_created_by>
        <sys_created_on>2023-07-31 01:34:33</sys_created_on>
        <sys_id>e06daa6697dc311015c7fbafe153af75</sys_id>
        <sys_mod_count>0</sys_mod_count>
        <sys_name>1</sys_name>
        <sys_package display_value="School Office Supplies Management" source="x_1080238_school_o">a783b0689700311015c7fbafe153af76</sys_package>
        <sys_policy/>
        <sys_scope display_value="School Office Supplies Management">a783b0689700311015c7fbafe153af76</sys_scope>
        <sys_update_name>sp_row_e06daa6697dc311015c7fbafe153af75</sys_update_name>
        <sys_updated_by>johniel.comanda</sys_updated_by>
        <sys_updated_on>2023-07-31 01:34:33</sys_updated_on>
    </sp_row>
</record_update>
